<?xml version="1.0" encoding="utf-8" ?>
<Defs>
	<HugsLib.UpdateFeatureDef Abstract="true" Name="ReinforcedMechanoid2_UpdateFeatureBase">
		<modNameReadable>ReinforcedMechanoid2</modNameReadable>
		<linkUrl>https://steamcommunity.com/sharedfiles/filedetails/?id=3400713047</linkUrl>
	</HugsLib.UpdateFeatureDef>
	<HugsLib.UpdateFeatureDef ParentName="ReinforcedMechanoid2_UpdateFeatureBase">
		<defName>ReinforcedMechanoid2_1_5_19</defName>
		<assemblyVersion>1.5.19</assemblyVersion>
		<content>This mod has been re-released for the new version of the game. This version will remain but will not be updated further.</content>
	</HugsLib.UpdateFeatureDef>
</Defs>

